{
	"name": "Sale-Small-INC",
	"properties": {
		"activities": [
			{
				"name": "COPY-DATA-INC",
				"type": "Copy",
				"dependsOn": [],
				"policy": {
					"timeout": "7.00:00:00",
					"retry": 0,
					"retryIntervalInSeconds": 30,
					"secureOutput": false,
					"secureInput": false
				},
				"userProperties": [],
				"typeProperties": {
					"source": {
						"type": "AzureSqlSource",
						"sqlReaderQuery": "SELECT [TransactionId]\n      ,[CustomerId]\n      ,[ProductId]\n      ,[Quantity]\n      ,[TransactionDate]\n      ,[Hour]\n      ,[Minute]\n      ,[StoreId]\n  FROM [dbo].[sale-small-modified]",
						"queryTimeout": "02:00:00",
						"partitionOption": "None"
					},
					"sink": {
						"type": "ParquetSink",
						"storeSettings": {
							"type": "AzureBlobFSWriteSettings"
						},
						"formatSettings": {
							"type": "ParquetWriteSettings"
						}
					},
					"enableStaging": false,
					"translator": {
						"type": "TabularTranslator",
						"mappings": [
							{
								"source": {
									"name": "TransactionId",
									"type": "String",
									"physicalType": "varchar"
								},
								"sink": {
									"name": "TransactionId",
									"type": "String",
									"physicalType": "UTF8"
								}
							},
							{
								"source": {
									"name": "CustomerId",
									"type": "Int32",
									"physicalType": "int"
								},
								"sink": {
									"name": "CustomerId",
									"type": "Int32",
									"physicalType": "INT_32"
								}
							},
							{
								"source": {
									"name": "ProductId",
									"type": "Int16",
									"physicalType": "smallint"
								},
								"sink": {
									"name": "ProductId",
									"type": "Int16",
									"physicalType": "INT_32"
								}
							},
							{
								"source": {
									"name": "Quantity",
									"type": "Byte",
									"physicalType": "tinyint"
								},
								"sink": {
									"name": "Quantity",
									"type": "Byte",
									"physicalType": "INT_32"
								}
							},
							{
								"source": {
									"name": "TransactionDate",
									"type": "Int32",
									"physicalType": "int"
								},
								"sink": {
									"name": "TransactionDate",
									"type": "Int32",
									"physicalType": "INT_32"
								}
							},
							{
								"source": {
									"name": "Hour",
									"type": "Byte",
									"physicalType": "tinyint"
								},
								"sink": {
									"name": "Hour",
									"type": "Byte",
									"physicalType": "INT_32"
								}
							},
							{
								"source": {
									"name": "Minute",
									"type": "Byte",
									"physicalType": "tinyint"
								},
								"sink": {
									"name": "Minute",
									"type": "Byte",
									"physicalType": "INT_32"
								}
							},
							{
								"source": {
									"name": "StoreId",
									"type": "Byte",
									"physicalType": "tinyint"
								},
								"sink": {
									"name": "StoreId",
									"type": "Byte",
									"physicalType": "INT_32"
								}
							}
						],
						"typeConversion": true,
						"typeConversionSettings": {
							"allowDataTruncation": true,
							"treatBooleanAsNumber": false
						}
					}
				},
				"inputs": [
					{
						"referenceName": "AzureSqlTable1",
						"type": "DatasetReference",
						"parameters": {
							"schema": "dbo",
							"nombretabla": "sale-small-modified"
						}
					}
				],
				"outputs": [
					{
						"referenceName": "salesforce_adls_parquet",
						"type": "DatasetReference",
						"parameters": {
							"container": "input",
							"directory": "salesForceInc",
							"filename": "sale-small-inc.parquet"
						}
					}
				]
			},
			{
				"name": "Data flow1",
				"type": "ExecuteDataFlow",
				"dependsOn": [
					{
						"activity": "COPY-DATA-INC",
						"dependencyConditions": [
							"Succeeded"
						]
					}
				],
				"policy": {
					"timeout": "1.00:00:00",
					"retry": 0,
					"retryIntervalInSeconds": 30,
					"secureOutput": false,
					"secureInput": false
				},
				"userProperties": [],
				"typeProperties": {
					"dataflow": {
						"referenceName": "DataFlowSalesForce",
						"type": "DataFlowReference"
					},
					"compute": {
						"coreCount": 8,
						"computeType": "General"
					},
					"traceLevel": "Fine"
				}
			}
		],
		"folder": {
			"name": "SalesForce"
		},
		"annotations": [],
		"lastPublishTime": "2021-10-27T18:10:39Z"
	},
	"type": "Microsoft.DataFactory/factories/pipelines"
}